[
  {
    "year": 2014,
    "value": 78.8414634146341
  },
  {
    "year": 2015,
    "value": 78.690243902439
  },
  {
    "year": 2016,
    "value": 78.5390243902439
  },
  {
    "year": 2017,
    "value": 78.5390243902439
  },
  {
    "year": 2018,
    "value": 78.6390243902439
  },
  {
    "year": 2019,
    "value": 78.7878048780488
  },
  {
    "year": 2020,
    "value": 76.9804878048781
  },
  {
    "year": 2021,
    "value": 76.3292682926829
  },
  {
    "year": 2022,
    "value": 77.4341463414634
  },
  {
    "year": 2023,
    "value": 78.3853658536585
  }
]