{
  "metadata": {
    "id": "ai_solar_panel_installations",
    "name": "Residential Solar Installations",
    "unit": "thousands of installations",
    "category": "environment",
    "description": "New residential solar panel installations",
    "source": "AI-Generated from SEIA installation data",
    "sourceUrl": "https://www.seia.org/solar-industry-research-data",
    "citation": "Solar Energy Industries Association Installation Reports (2014-2024)",
    "isAIGenerated": true,
    "aiGeneratedAt": "2025-10-07T12:36:02.819Z",
    "filename": "environment-residential-solar-installations"
  },
  "data": [
    {
      "year": 2014,
      "value": 197.45,
      "generatedAt": "2025-10-07T12:36:02.824Z"
    },
    {
      "year": 2015,
      "value": 223.47,
      "generatedAt": "2025-10-07T12:36:02.824Z"
    },
    {
      "year": 2016,
      "value": 245.49,
      "generatedAt": "2025-10-07T12:36:02.824Z"
    },
    {
      "year": 2017,
      "value": 248.36,
      "generatedAt": "2025-10-07T12:36:02.824Z"
    },
    {
      "year": 2018,
      "value": 321.72,
      "generatedAt": "2025-10-07T12:36:02.824Z"
    },
    {
      "year": 2019,
      "value": 411.35,
      "generatedAt": "2025-10-07T12:36:02.824Z"
    },
    {
      "year": 2020,
      "value": 432.32,
      "generatedAt": "2025-10-07T12:36:02.824Z"
    },
    {
      "year": 2021,
      "value": 371.94,
      "generatedAt": "2025-10-07T12:36:02.824Z"
    },
    {
      "year": 2022,
      "value": 511.34,
      "generatedAt": "2025-10-07T12:36:02.824Z"
    },
    {
      "year": 2023,
      "value": 594.24,
      "generatedAt": "2025-10-07T12:36:02.824Z"
    },
    {
      "year": 2024,
      "value": 551.44,
      "generatedAt": "2025-10-07T12:36:02.824Z"
    }
  ]
}