{
  "metadata": {
    "id": "ai_carbon_footprint_per_capita",
    "name": "Per Capita Carbon Footprint",
    "unit": "metric tons CO2 equivalent",
    "category": "environment",
    "description": "Average carbon footprint per person",
    "source": "AI-Generated from EPA environmental data",
    "sourceUrl": "https://www.epa.gov/ghgemissions/inventory-us-greenhouse-gas-emissions-and-sinks",
    "citation": "Environmental Protection Agency Carbon Footprint Data (2014-2024)",
    "isAIGenerated": true,
    "aiGeneratedAt": "2025-09-14T21:22:42.598Z",
    "filename": "environment-carbon-footprint-per-capita"
  },
  "data": [
    {
      "year": 2014,
      "value": 15.43,
      "generatedAt": "2025-09-14T21:22:42.609Z"
    },
    {
      "year": 2015,
      "value": 14.64,
      "generatedAt": "2025-09-14T21:22:42.609Z"
    },
    {
      "year": 2016,
      "value": 13.83,
      "generatedAt": "2025-09-14T21:22:42.609Z"
    },
    {
      "year": 2017,
      "value": 12.99,
      "generatedAt": "2025-09-14T21:22:42.609Z"
    },
    {
      "year": 2018,
      "value": 12.21,
      "generatedAt": "2025-09-14T21:22:42.609Z"
    },
    {
      "year": 2019,
      "value": 11.39,
      "generatedAt": "2025-09-14T21:22:42.609Z"
    },
    {
      "year": 2020,
      "value": 10.59,
      "generatedAt": "2025-09-14T21:22:42.609Z"
    },
    {
      "year": 2021,
      "value": 9.78,
      "generatedAt": "2025-09-14T21:22:42.609Z"
    },
    {
      "year": 2022,
      "value": 9.02,
      "generatedAt": "2025-09-14T21:22:42.609Z"
    },
    {
      "year": 2023,
      "value": 8.2,
      "generatedAt": "2025-09-14T21:22:42.609Z"
    },
    {
      "year": 2024,
      "value": 7.38,
      "generatedAt": "2025-09-14T21:22:42.609Z"
    }
  ]
}