{
  "metadata": {
    "id": "ai_ai_patent_filings",
    "name": "AI Patent Applications",
    "unit": "number of patents",
    "category": "technology",
    "description": "Annual AI-related patent applications filed",
    "source": "AI-Generated from USPTO patterns",
    "sourceUrl": "https://www.uspto.gov/web/offices/ac/ido/oeip/taf/reports.htm",
    "citation": "US Patent & Trademark Office AI Classification (2014-2024)",
    "isAIGenerated": true,
    "aiGeneratedAt": "2025-10-07T12:15:44.623Z",
    "filename": "technology-ai-patent-applications"
  },
  "data": [
    {
      "year": 2014,
      "value": 5311.66,
      "generatedAt": "2025-10-07T12:15:44.626Z"
    },
    {
      "year": 2015,
      "value": 7653.78,
      "generatedAt": "2025-10-07T12:15:44.626Z"
    },
    {
      "year": 2016,
      "value": 3663.97,
      "generatedAt": "2025-10-07T12:15:44.626Z"
    },
    {
      "year": 2017,
      "value": 8865.43,
      "generatedAt": "2025-10-07T12:15:44.626Z"
    },
    {
      "year": 2018,
      "value": 846.96,
      "generatedAt": "2025-10-07T12:15:44.626Z"
    },
    {
      "year": 2019,
      "value": 10746.11,
      "generatedAt": "2025-10-07T12:15:44.626Z"
    },
    {
      "year": 2020,
      "value": 11160.12,
      "generatedAt": "2025-10-07T12:15:44.626Z"
    },
    {
      "year": 2021,
      "value": 5342.88,
      "generatedAt": "2025-10-07T12:15:44.626Z"
    },
    {
      "year": 2022,
      "value": 18547.62,
      "generatedAt": "2025-10-07T12:15:44.626Z"
    },
    {
      "year": 2023,
      "value": 6480.06,
      "generatedAt": "2025-10-07T12:15:44.626Z"
    },
    {
      "year": 2024,
      "value": 14425.36,
      "generatedAt": "2025-10-07T12:15:44.626Z"
    }
  ]
}