[
  {
    "city": "New York",
    "country": "US",
    "coordinates": {
      "lat": 40.7128,
      "lon": -74.006
    },
    "temperature": -1.66,
    "humidity": 44,
    "pressure": 1034,
    "windSpeed": 4.47,
    "cloudiness": 0,
    "visibility": 10000,
    "weatherCondition": "Clear",
    "description": "clear sky",
    "timestamp": "2026-03-02T06:16:59.508Z",
    "year": 2026,
    "month": 3,
    "day": 2
  },
  {
    "city": "London",
    "country": "GB",
    "coordinates": {
      "lat": 51.5074,
      "lon": -0.1278
    },
    "temperature": 8.87,
    "humidity": 81,
    "pressure": 1013,
    "windSpeed": 3.6,
    "cloudiness": 86,
    "visibility": 10000,
    "weatherCondition": "Clouds",
    "description": "overcast clouds",
    "timestamp": "2026-03-02T06:17:00.723Z",
    "year": 2026,
    "month": 3,
    "day": 2
  },
  {
    "city": "Tokyo",
    "country": "JP",
    "coordinates": {
      "lat": 35.6762,
      "lon": 139.6503
    },
    "temperature": 13.05,
    "humidity": 68,
    "pressure": 1021,
    "windSpeed": 5.66,
    "cloudiness": 75,
    "visibility": 10000,
    "weatherCondition": "Clouds",
    "description": "broken clouds",
    "timestamp": "2026-03-02T06:17:01.946Z",
    "year": 2026,
    "month": 3,
    "day": 2
  },
  {
    "city": "Sydney",
    "country": "AU",
    "coordinates": {
      "lat": -33.8688,
      "lon": 151.2093
    },
    "temperature": 25.62,
    "humidity": 72,
    "pressure": 1009,
    "windSpeed": 8.75,
    "cloudiness": 97,
    "visibility": 10000,
    "weatherCondition": "Rain",
    "description": "light rain",
    "timestamp": "2026-03-02T06:17:03.160Z",
    "year": 2026,
    "month": 3,
    "day": 2
  },
  {
    "city": "Mumbai",
    "country": "IN",
    "coordinates": {
      "lat": 19.076,
      "lon": 72.8777
    },
    "temperature": 30.03,
    "humidity": 58,
    "pressure": 1013,
    "windSpeed": 4.63,
    "cloudiness": 1,
    "visibility": 3500,
    "weatherCondition": "Smoke",
    "description": "smoke",
    "timestamp": "2026-03-02T06:17:04.373Z",
    "year": 2026,
    "month": 3,
    "day": 2
  },
  {
    "city": "São Paulo",
    "country": "BR",
    "coordinates": {
      "lat": -23.5505,
      "lon": -46.6333
    },
    "temperature": 17.09,
    "humidity": 88,
    "pressure": 1014,
    "windSpeed": 2.57,
    "cloudiness": 75,
    "visibility": 10000,
    "weatherCondition": "Clouds",
    "description": "broken clouds",
    "timestamp": "2026-03-02T06:17:05.587Z",
    "year": 2026,
    "month": 3,
    "day": 2
  },
  {
    "city": "Cairo",
    "country": "EG",
    "coordinates": {
      "lat": 30.0444,
      "lon": 31.2357
    },
    "temperature": 12.33,
    "humidity": 62,
    "pressure": 1021,
    "windSpeed": 2.06,
    "cloudiness": 40,
    "visibility": 3000,
    "weatherCondition": "Haze",
    "description": "haze",
    "timestamp": "2026-03-02T06:17:06.802Z",
    "year": 2026,
    "month": 3,
    "day": 2
  },
  {
    "city": "Moscow",
    "country": "RU",
    "coordinates": {
      "lat": 55.7558,
      "lon": 37.6173
    },
    "temperature": 1.26,
    "humidity": 98,
    "pressure": 1011,
    "windSpeed": 3.46,
    "cloudiness": 100,
    "visibility": 299,
    "weatherCondition": "Clouds",
    "description": "overcast clouds",
    "timestamp": "2026-03-02T06:17:08.035Z",
    "year": 2026,
    "month": 3,
    "day": 2
  },
  {
    "city": "Dubai",
    "country": "AE",
    "coordinates": {
      "lat": 25.2048,
      "lon": 55.2708
    },
    "temperature": 31.01,
    "humidity": 23,
    "pressure": 1012,
    "windSpeed": 5.14,
    "cloudiness": 0,
    "visibility": 10000,
    "weatherCondition": "Clear",
    "description": "clear sky",
    "timestamp": "2026-03-02T06:17:09.253Z",
    "year": 2026,
    "month": 3,
    "day": 2
  },
  {
    "city": "Toronto",
    "country": "CA",
    "coordinates": {
      "lat": 43.6532,
      "lon": -79.3832
    },
    "temperature": -13.04,
    "humidity": 79,
    "pressure": 1037,
    "windSpeed": 5.81,
    "cloudiness": 9,
    "visibility": 10000,
    "weatherCondition": "Clear",
    "description": "clear sky",
    "timestamp": "2026-03-02T06:17:10.474Z",
    "year": 2026,
    "month": 3,
    "day": 2
  }
]